{
    "@context": "https://schema.org/",
    "@type": "Dataset",
    "_id": "zenodo_10889015",
    "_ignored": [
        "all.keyword"
    ],
    "_score": 13.150123,
    "author": [
        {
            "name": "Fitspresso"
        }
    ],
    "curatedBy": {
        "@type": "Organization",
        "name": "Zenodo",
        "url": "https://zenodo.org/",
        "versionDate": "2024-08-21"
    },
    "date": "2024-03-28",
    "dateModified": "2024-03-28",
    "datePublished": "2024-03-28T00:00:00",
    "description": "FitSpresso Reviews, FitSpresso stands out as an exceptional product for weight reduction, providing a natural boost to your metabolism and supplying ample energy to expedite your weight loss journey. Packed with ingredients like Capsicum annum, chromium picolinate, Panax ginseng, L-carnitine, among others, FitSpresso comes in a convenient capsule form.\n\nClick Here To Buy Now From Official Website Of Fitspresso\n\nHere, you will find the pros are placed against the cons. This will give you the easiest way to analyze its effectiveness.\n\nHow To Properly Consume FitSpresso Tablets?\n\nLearning about supplement consumption is the next decisive step. On examining the capsules, it is clear that they are easy to swallow and this makes them pretty simple to consume.\u00a0\n\nAs each bottle contains 60 vegetarian FitSpresso capsules sufficient for a month, you can take two capsules each day. Take them along with your morning coffee and you will start experiencing the fat-burning symptoms in no time.One thing to remember here is to consume the formula regularly. This ensures proper absorption of nutrients into your body. Now if you are curious as to how long it takes to see results, let me clear that for you.\u00a0\n\nFitSpresso results can appear differently for everyone yet if you follow a regular pattern, you will notice faster results. It is advisable to take the formula for at least 3-6 months to ensure optimum benefits.\u00a0\n\nFitSpresso Customer Reviews: Are They Satisfied?\n\nWhen a dietary supplement is found valid, there will naturally be a solid customer base to support its validity. In the case of FitSpresso, you can find similarly strong customer support. This is proven by the thousands of FitSpresso customer reviews available through social media platforms like Reddit and Facebook.\n\nThose who have consumed FitSpresso tablets have shared their success stories through various channels. Some of these customers claim to have lost around 64 pounds within weeks.\u00a0\n\nMost of these customers belong to middle age and have tried every other means for weight loss. It was a last resort that they came across and used it with hesitation. But surprisingly, the formula ignited their fat molecules leading them to the path of weight loss.\u00a0\n\nWe couldn\u2019t find any relevant negative reviews or complaints anywhere. So it can be said that the lion\u2019s share of the FitSpresso reviews are positive and symbolize the ample customer base it has.\u00a0\n\nClick Here To Buy Now From Official Website Of Fitspresso\n\nMore Link\n\nhttps://www.facebook.com/fitSpressousaaweightloss/",
    "distribution": [
        {
            "contentUrl": "https://zenodo.org/api/records/10889016/files-archive",
            "dateModified": "2024-03-28"
        }
    ],
    "doi": "10.5281/zenodo.10889015",
    "identifier": "zenodo.10889015",
    "includedInDataCatalog": {
        "@type": "Organization",
        "name": "Zenodo",
        "url": "https://zenodo.org/",
        "versionDate": "2024-08-21"
    },
    "license": "https://creativecommons.org/licenses/by/4.0/legalcode",
    "name": "Fitspresso US Honest Review It's Indigents & Benifits Official WebSite, Where To Buy",
    "sameAs": [
        "https://zenodo.org/records/10889016"
    ],
    "url": "https://zenodo.org/record/10889015"
}