{
    "@context": "https://schema.org/",
    "@type": "Dataset",
    "_id": "zenodo_11126724",
    "_ignored": [
        "all.keyword"
    ],
    "_score": 5.5669875,
    "author": [
        {
            "name": "makersscam, smith"
        }
    ],
    "curatedBy": {
        "@type": "Organization",
        "name": "Zenodo",
        "url": "https://zenodo.org/",
        "versionDate": "2024-08-21"
    },
    "date": "2024-05-07",
    "dateModified": "2024-05-07",
    "datePublished": "2024-05-07T00:00:00",
    "description": "At the point when we revel in torment our body answers in any case each time. Be that as it may, the greatest significant part of enduring material or scholarly torment is surpassing the resilience downside each time. We need to expect that while encountering hurt our body answers at the person's lenient level. They might change from each unique. In any case, there is no such supplementation or reflection of the impact that would make our edge cross numb and dormant because of the reality each residence component stories hurt, nervousness, and anguish in its different ways. However, one issue that we can address is to ease scholarly and actual Joint throb by endeavoring\u00a0Green Acre CBD Gummies\u00a0for recuperating benefits. Therefore, we will be equipped to live our lives in significantly less pain and with pleasant changes.\n\n\n\nGreen Acre CBD Gummies Reviews Uncovered\n\n\u00a0\n\nThe responses may also shift for each person based on their involvement with hurt administration and tension medicines. Notwithstanding, there are a couple of homegrown answers equipped with pressure-easing houses called Cannabinoids. This arrangement is commonly promoted as CBD chewy candies which is a sugar-improving sweet region with CBD possessions for torment mitigation and strain control. Green Acre CBD Gummies grandstands a couple of pretty specific qualities in expressions of throb cure homes and yelping at the genuine capability of CBD(Cannabidiol) and its vital equation to improve human culture.\n\n\u27a2\u27a2\u27a2 Click Here to Buy Green Acre CBD Gummies From Official Website \u27a2\u27a2\u27a2\n\n\u00a0\n\nWhat do you need to treat your regular frame ache?\n\n\u00a0\n\nWhile examining the capacity advantages of cannabinoids the maker of Green Acre CBD Gummies assurances to ease real and scholarly agony in your body with non-angle results. In any case, it comes inside the type of dietary supplementation in a Sticky through shape making it easily satisfactory consistently. Moreover, it likewise ends up telling the truth in treating joint portability, lower leg torment, and strain the board for a higher way of life.\n\n\n\nGreen Acre CBD Gummies is a complete healthcare solution\n\nThe components play a significant situation in expressions of strain help and torment control since they use a crucial stockpile of CBD(Cannabidiol) that is hemp vegetation. Accordingly, CBD can alter ECS(Endocannabinoid Framework) empowering better capacity of the unfortunate framework and forestalling mind haze, body hurt, joint issues, and upsetting way of life. These are some of the significant components featured inside the usage of Green Acre CBD Gummies.\n\n\u27a2\u27a2\u27a2 Visit The Official Site Here To Buy Green Acre CBD Gummies \u27a2\u27a2\u27a2\n\nGreen Acre CBD Gummies' vital ingredients\n\nGreen Acre CBD Gummies intrigue each individual who needs to facilitate their psychological and substantial hurt with the natural response. Luckily, it offers a dispersion of cannabinoids using the bloodless-dire extraction strategy. As by the specialists, CBD can be fine extricated using a virus-squeezing strategy allowing extra Cannabinoids to assist you with defeating your substantial and mental aggravation with no feature results. Recorded underneath is an amount of the best passing components presented inside the fundamental plan:-\n\n\n\nHemp plant removal This plant is explicitly developed for the extraction of CBD (Cannabidiol) radically selling normal prosperity and a casual way of life.\n\nCannabinoids is a promising well-being plan that allows your body to fix the ECS(Endocannabinoid Framework) to improve your physical and emotional well-being.\n\nGelatin miles a sugar substance that offers a gooey surface to Sticky bears adding all the more sweet and pungent flavors to CBD sticky.\n\nBoswellia Serrata Concentrate on treating joint torment and body disease is a particular part of empowering the success of home-grown arrangements excellently.\n\nNourishment D-supplements and minerals play a monster capability in the administration of your body mulling over everything as a well-being stage for the ECS(Endocannabinoid Framework) Green Acre CBD Gummies present pivotal nutrients and wholesome expense on your body for solid usefulness.\n\n\n\n\nGreen Acre CBD Gummies fine advantages\n\n\u00a0\n\nThe creators of Green Acre CBD Gummies truly need to facilitate the substantial and scholarly hurt without striking any drug medication to appear to be legit guaranteed about CBD chewy candies rather than wary around the idea of natural smoothness and prosperity capabilities. A portion of the top-notch perceived endowments of taking the supplement have been referenced below:-\n\n\n\nFacilitates mental and actual agony This attestation is regularly named the sacred goal of CBD chewy candies as it without any help portrays the sole rationale of CBD in human existence.\n\nTreat joint inconveniences As we age we tend to widen weakness in our joints because of the becoming older procedure anyway in the wake of taking CBD Chewy candies, joint portability is a monster step toward treatment.\n\nTranquility and prosperity CBD surely further develops famous Well-being prosperity by integrating it into your upsetting ways of life and facilitating mental hurt.\n\nFix rest cycle-outline bothering and joint torment will make your evenings home damnation because of the ordinary awakening of hurt sensation. CBD chewy candies normally fix the pen sensation for higher rest.\n\nSupport ECS(Endocannabinoid Framework)- ECS serves a basic reason in holding your substantial authorization ideal yet without even a trace of CBD(Cannabidiol) hurt sensation could break your physical and scholarly well-being.\n\n\n>> Order Green Acre CBD Gummies Official Website Get Exclusive Offer >>\n\nGreen Acre CBD Gummies measurement instructive for ensured outcomes\n\n\u00a0\n\nIf you have any desire to get each of the above benefits of Green Acre CBD Gummies then you need to notice a specific measurement plan coordinated by the item maker who best fills an unmarried need to acquire human existence inside the top-notch way conceivable. Thus you could begin accepting CBD chewy candies by the suggested dose noted in the container which is chewy candies consistently. Above all the creators have guaranteed that you get hold of more delicious and fortifying CBD chewy candies with no feature outcomes. To utilize it securely there's one situation that you want to maintain utilizing that is don't surpass the pushed measurement admission for wellbeing thought processes.\n\n\n\n\u00a0\n\nGreen Acre CBD Gummies: How to use?\n\n\u00a0\n\nJonson Aamie 47 Years wants to quiet my body and psyche for higher information on this tumultuous way of life. Yet, tragically, I wasn't ready for any THC(Tetrahydrocannabinol). So I have tried every prosperity supplement. However, here I obtained a lot of late and unrivaled endowments pleasantly. Green Acre CBD Gummies turns into a cross-to supplement that ensures hurt and stress mitigation. In particular, I took the empowered dose as an incentive for the quick 30 days. At last, I get better day to day with tossing in any kind of extravagant terms.\n\n\u00a0\n\n\u27a3 \u27a3 Buy Now With Huge Discount \u2964\u2964 Official Website Visit Now\n\nWhere to buy Green Acre CBD Gummies?\n\n\u00a0\n\nGreen Acre CBD Gummies are the easiest that anyone could hope to find online. So on the off chance that you need to digitally book your most memorable request then genuinely click at the flag above and fill in the entirety of your subtleties well with no mistaken measurements.\n\n\u00a0\n\nREAD MORE --->\u00a0\n\nhttps://www.mynewsdesk.com/iexponet/pressreleases/green-acre-cbd-gummies-reviews-clinically-proven-in-us-3321014\n\nhttps://sites.google.com/view/makers-cbdgummies-buy/home\n\nhttps://colab.research.google.com/drive/15X9gGv7FzhVmYCfwKrSSasafrFsqfzE_#scrollTo=Wf5KrEb6vrkR\n\nhttps://makerscbdgummiesbuy.webflow.io/\n\nhttps://makerscbdgummies35.godaddysites.com/\n\nhttps://www.eventbrite.com/e/makers-cbd-gummies-review-is-this-blood-sugar-supplement-legit-tickets-899137423237?aff=oddtdtcreator\n\nhttps://medium.com/@makersalert/makers-cbd-gummies-review-is-this-blood-sugar-supplement-legit-03e56bd1424f\n\nhttps://www.yepdesk.com/makers-cbd-gummies-review-is-this-blood-sugar-supplement-legit-\n\nhttps://makers-cbd-gummies-reviews-alert.hashnode.dev/makers-cbd-gummies-to-support-blood-sugar-and-blood-pressure-benefits-price\n\nhttps://hackmd.io/@makersalert/makers-cbd-gummies-to-support-blood-sugar-and-blood-pressure-benefits-price\n\nhttps://twor.microsoftcrmportals.com/forums/general-discussion/ece158b5-ad0b-ef11-a73c-00224895e725\n\nhttps://indspire.microsoftcrmportals.com/en-US/forums/general-discussion/68d6f871-ad0b-ef11-a73d-6045bd5b9c00\n\nhttps://mbolatam.microsoftcrmportals.com/forums/general-discussion/59ef0874-ad0b-ef11-9899-002248e1334c\n\nhttps://ecosoft.microsoftcrmportals.com/en-US/forums/general-discussion/ec30fd73-ad0b-ef11-a81c-6045bda1d753\n\nhttps://thecontingent.microsoftcrmportals.com/forums/general-discussion/dd954275-ad0b-ef11-a73d-6045bd01c1cc\n\nhttps://fms.microsoftcrmportals.com/forums/general-discussion/0396bb73-ad0b-ef11-a73c-6045bd20e9c7\n\nhttps://makerscbdgummiesreviews.webflow.io/\n\nhttps://makerscbdgummiesreviews5.godaddysites.com/\n\nhttps://medium.com/@makersscam/makers-cbd-gummies-reviews-side-effects-best-results-works-buy-38753b70347d",
    "distribution": [
        {
            "contentUrl": "https://zenodo.org/api/records/11126725/files-archive",
            "dateModified": "2024-05-07"
        }
    ],
    "doi": "10.5281/zenodo.11126724",
    "identifier": "zenodo.11126724",
    "includedInDataCatalog": {
        "@type": "Organization",
        "name": "Zenodo",
        "url": "https://zenodo.org/",
        "versionDate": "2024-08-21"
    },
    "license": "https://creativecommons.org/licenses/by/4.0/legalcode",
    "name": "Green Acre CBD Gummies: Really Working (Review & Price) Is It Safe?",
    "sameAs": [
        "https://zenodo.org/records/11126725"
    ],
    "url": "https://zenodo.org/record/11126724"
}