{
    "@context": "https://schema.org/",
    "@type": "Dataset",
    "_id": "zenodo_11312801",
    "_ignored": [
        "all.keyword"
    ],
    "_score": 11.096276,
    "author": [
        {
            "affiliation": {
                "name": "Northwestern University"
            },
            "identifier": "0000-0001-8743-5944",
            "name": "Adney, Scott"
        }
    ],
    "curatedBy": {
        "@type": "Organization",
        "name": "Zenodo",
        "url": "https://zenodo.org/",
        "versionDate": "2024-08-21"
    },
    "date": "2024-05-31",
    "dateModified": "2024-05-31",
    "datePublished": "2024-05-26T00:00:00",
    "description": "\u00a0\n\n\u26a0\ufe0fLimited Stock Alert!\u26a0\ufe0f\n\n\u00a0\n\n\u2714Product Name - BioGreen CBD Blood Sugar Gummies\n\n\u2714Side Effect - No Side Effects\n\n\u2714Availability - Online\n\n\u2714Rating -\u2b50\u2b50\u2b50\u2b50\u2b50\n\n\u2714For Order Official Website - https://nutraweb24x7.com/get-guardian-botanicals-blood-balance/\n\n\u00a0\n\nHurry Up - Limited Time Offer - Buy Now\n\nHurry Up - Limited Time Offer - Buy Now\n\nHurry Up - Limited Time Offer - Buy Now\n\n\u00a0\n\nBioGreen CBD Blood Sugar Gummies\n\nManaging blood sugar levels can be a real challenge, but with the right tools, it becomes much more manageable. Enter BioGreen CBD Blood Sugar Gummies, a product designed to help regulate blood sugar levels naturally and effectively. Whether you're dealing with diabetes or just trying to keep your blood sugar in check, these gummies could be a game-changer. But what exactly are they, and how do they work? Let's dive in.\n\n\u00a0\n\nWhat Are BioGreen CBD Blood Sugar Gummies?\n\nBioGreen CBD Blood Sugar Gummies are a dietary supplement formulated to help maintain healthy blood sugar levels. They combine the power of CBD with other natural ingredients known for their health benefits. These gummies are easy to incorporate into your daily routine and offer a delicious way to support your health.\n\n\u00a0\n\nSpecial Price for Sale: BioGreen CBD Blood Sugar Gummies from the Official Website Online\n\n\u00a0\n\nUnderstanding Blood Sugar Levels\n\nBlood sugar, or glucose, is the main sugar found in your blood and your body's primary source of energy. Maintaining the right balance of blood sugar is crucial for overall health. High blood sugar levels can lead to diabetes and other health issues, while low blood sugar can cause dizziness, fatigue, and more. Keeping these levels stable is essential for feeling your best every day.\n\n\u00a0\n\nThe Role of CBD in Blood Sugar Management\n\nCBD, or cannabidiol, is a compound found in cannabis plants. It's known for its various health benefits, including pain relief, anxiety reduction, and more. But did you know it can also help with blood sugar management? Studies have shown that CBD can help regulate blood sugar levels by improving the body's metabolism and reducing inflammation. This makes it a promising option for those looking to manage their blood sugar naturally.\n\n\u00a0\n\nExclusive Details: BioGreen CBD Blood Sugar Gummies Read More Details on Official Website!\n\n\u00a0\n\nIngredients in BioGreen CBD Blood Sugar Gummies\n\nThese gummies are packed with ingredients that are beneficial for blood sugar management. Here's a closer look at what's inside:\n\n\u00a0\n\nCBD: Helps regulate blood sugar and reduce inflammation.\n\nChromium: A mineral that enhances insulin sensitivity.\n\nBerberine: A compound that has been shown to lower blood sugar levels.\n\nCinnamon Extract: Known for its ability to improve insulin sensitivity.\n\nAlpha Lipoic Acid: Helps reduce oxidative stress and improve insulin sensitivity.\n\nEach ingredient plays a crucial role in helping maintain healthy blood sugar levels, making these gummies a powerful tool in your health arsenal.\n\n\u00a0\n\nHow BioGreen CBD Blood Sugar Gummies Work?\n\nThese gummies work by interacting with your body's endocannabinoid system, which plays a role in regulating various functions, including metabolism and blood sugar levels. When you consume the gummies, the CBD and other ingredients get to work, helping to balance your blood sugar levels naturally. Many users have reported positive experiences, noting improvements in their blood sugar levels and overall health.\n\n\u00a0\n\nVisit Here Know More: Click Here To Go to Official Website Now BioGreen CBD Blood Sugar Gummies\n\n\u00a0\n\nBenefits of BioGreen CBD Blood Sugar Gummies\n\nUsing BioGreen CBD Blood Sugar Gummies offers numerous benefits:\n\n\u00a0\n\nRegulates Blood Sugar: Helps keep your blood sugar levels stable.\n\nImproves Insulin Sensitivity: Makes your body more efficient at using insulin.\n\nReduces Inflammation: Helps lower inflammation, which can affect blood sugar levels.\n\nBoosts Overall Health: Supports various aspects of your health, from metabolism to mood.\n\nCompared to other blood sugar management methods, these gummies offer a natural and convenient solution without the need for harsh chemicals or complicated routines.\n\n\u00a0\n\nHow to Use BioGreen CBD Blood Sugar Gummies?\n\nTo get the most out of these gummies, it's essential to use them correctly. Here are some tips:\n\n\u00a0\n\nRecommended Dosage: Follow the dosage instructions on the packaging. Typically, it's one or two gummies per day.\n\nBest Practices: Take the gummies at the same time each day for consistency.\n\nPotential Side Effects: While generally safe, some people may experience mild side effects like dry mouth or drowsiness. If you have any concerns, consult with your doctor.\n\n\u00a0\n\nMUST SEE: Click Here to Order BioGreen CBD Blood Sugar Gummies For The Best Price Available!\n\n\u00a0\n\nUser Testimonials and Reviews\n\nMany people have found success with BioGreenCBD Blood Sugar Gummies. Here are a few stories:\n\n\u00a0\n\nJohn: \"I've been using these gummies for a few months, and my blood sugar levels have never been better. They taste great too!\"\n\nSarah: \"These gummies have been a lifesaver. I was struggling to keep my blood sugar stable, but now I feel more in control.\"\n\nDr. Smith: \"As a healthcare professional, I recommend BioGreenCBD Blood Sugar Gummies to my patients looking for a natural way to manage their blood sugar.\"\n\n\u00a0\n\nWhere to Buy BioGreen CBD Blood Sugar Gummies?\n\nYou can purchase BioGreen CBD Blood Sugar Gummies from the official website or authorized retailers. Be sure to take advantage of any discounts or special offers available. Check the shipping and return policies to ensure a smooth purchasing experience.\n\n\u00a0\n\nConclusion\n\nBioGreenCBD Blood Sugar Gummies are a natural, effective way to manage blood sugar levels. With their blend of CBD and other powerful ingredients, they offer a convenient solution for those looking to improve their health. If you're struggling with blood sugar management, these gummies could be just what you need.\n\n\u00a0\n\nOfficial Website:- https://nutraweb24x7.com/get-guardian-botanicals-blood-balance/\n\n\u00a0\n\n\u00a0",
    "distribution": [
        {
            "contentUrl": "https://zenodo.org/api/records/11312802/files-archive",
            "dateModified": "2024-05-31"
        }
    ],
    "doi": "10.5281/zenodo.11312801",
    "identifier": "zenodo.11312801",
    "inLanguage": {
        "name": "eng"
    },
    "includedInDataCatalog": {
        "@type": "Organization",
        "name": "Zenodo",
        "url": "https://zenodo.org/",
        "versionDate": "2024-08-21"
    },
    "keywords": [
        "BioGreen CBD Blood Sugar Gummies"
    ],
    "license": "https://creativecommons.org/licenses/by/4.0/legalcode",
    "name": "BioGreen CBD Blood Sugar Support Gummies - Balances Blood Sugar Levels And Blood Pressure Is It Safe To Use?",
    "sameAs": [
        "https://zenodo.org/records/11312802"
    ],
    "url": "https://zenodo.org/record/11312801"
}